{
  "chapter_id": "job28",
  "testament": "ot",
  "book_dir": "job",
  "chapter_num": 28,
  "title": "Job 28",
  "subtitle": "The Wisdom Hymn: Where Shall Wisdom Be Found?",
  "timeline_link": {
    "event_id": "book-job",
    "text": "See on Timeline — Job Written"
  },
  "map_story_link": null,
  "sections": [
    {
      "section_num": 1,
      "header": "Verses 1–11 — Human Mining: We Dig for Gold and Sapphires",
      "verse_start": 1,
      "verse_end": 11,
      "panels": {
        "heb": [
          {
            "word": "מָקוֹם",
            "transliteration": "māqōm",
            "gloss": "place / source / mine",
            "paragraph": "\"There is a mine (māqōm) for silver and a place where gold is refined\" (v.1). The chapter opens with human technological achievement: mining, smelting, tunnelling. We can find silver, gold, iron, copper, sapphires — we can dig through rock and overturn mountains. Human ingenuity is extraordinary."
          }
        ],
        "cross": {
          "refs": [
            {
              "ref": "Prov 2:4–5",
              "note": "\"Search for it as for hidden treasure... then you will understand the fear of the LORD\" — the same search metaphor."
            },
            {
              "ref": "Prov 8:10–11",
              "note": "\"Choose my instruction instead of silver\" — wisdom valued above precious metals."
            }
          ]
        },
        "mac": {
          "source": "MacArthur Study Bible — Faithful Paraphrase",
          "notes": [
            {
              "ref": "28:1–4",
              "note": "\"There is a mine for silver, a place where gold is refined. Iron is taken from the earth, copper smelted from ore.\" Human technology is celebrated: we can extract what is hidden."
            },
            {
              "ref": "28:5–8",
              "note": "\"The earth, from which food comes, is transformed below as by fire. Sapphires come from its rocks. No bird of prey knows that hidden path.\" Mining goes where even eagles cannot see. Human achievement reaches into the earth’s depths."
            },
            {
              "ref": "28:9–11",
              "note": "\"Human hands assault the flinty rock and lay bare the roots of the mountains. They tunnel through the rock; their eyes see all its treasures.\" But the greatest treasure — wisdom — remains beyond reach."
            }
          ]
        },
        "calvin": {
          "source": "John Calvin, Commentaries — Faithful Paraphrase",
          "notes": [
            {
              "ref": "28:1–4",
              "note": "Calvin: the catalogue of human industry honours God’s gift of intelligence to humanity. We are not criticised for mining; we are shown its limits."
            },
            {
              "ref": "28:9–11",
              "note": "Calvin: \"they lay bare the roots of the mountains\" — human power is real but relative. What we uncover physically, we cannot uncover spiritually."
            }
          ]
        },
        "net": {
          "source": "NET Bible Full Notes Edition — Biblical Studies Press",
          "notes": [
            {
              "ref": "28:1",
              "note": "The NET: māqōm means both \"place\" and \"source.\" There is a source for silver — but is there a source for wisdom?"
            },
            {
              "ref": "28:3–4",
              "note": "The NET discusses the mining techniques described: fire-setting (heating rock to crack it), shaft-sinking, water management. These are accurately attested in ancient Near Eastern mining."
            }
          ]
        },
        "clines": {
          "source": "David J.A. Clines, Job, WBC (3 vols., 1989–2011) — Scholarly Paraphrase",
          "notes": [
            {
              "ref": "28:1–11",
              "note": "Clines: the mining section is the most detailed technological description in the OT. The poet knew mining operations: shafts, tunnels, fire-setting to crack rock, water diversion. The point: human skill is immense. It is not enough for wisdom."
            },
            {
              "ref": "28:7–8",
              "note": "Clines: \"no bird of prey knows that hidden path\" — eagles have the sharpest eyes in the animal kingdom. Even they cannot see what miners see. But miners cannot see what only God sees."
            }
          ]
        },
        "habel": {
          "source": "Norman C. Habel, The Book of Job, OTL (1985) — Scholarly Paraphrase",
          "notes": [
            {
              "ref": "28:1–11",
              "note": "Habel: the wisdom hymn is the narrator’s commentary on the entire dialogue. The friends sought wisdom through tradition; Job sought it through experience. Both failed. The chapter explains why."
            }
          ]
        },
        "hist": {
          "context": "The voice shifts from Job to the narrator (or to a poetic interlude). The wisdom hymn stands between the dialogue (ch 3–27) and Job’s final defence (ch 29–31). It asks the book’s deepest question: where is wisdom found? The mining imagery establishes the premise: humans can find anything hidden in the earth. But wisdom is more hidden than any mineral."
        }
      }
    },
    {
      "section_num": 2,
      "header": "Verses 12–28 — “The Fear of the Lord — That Is Wisdom”",
      "verse_start": 12,
      "verse_end": 28,
      "panels": {
        "heb": [
          {
            "word": "חָכְמָה",
            "transliteration": "ḥok̅mâ",
            "gloss": "wisdom",
            "paragraph": "\"Where can wisdom (ḥok̅mâ) be found? Where does understanding dwell?\" (v.12). The question is repeated in v.20. Wisdom cannot be found in the land of the living (v.13), in the deep sea (v.14), or bought with gold, silver, onyx, or sapphire (vv.15–19). Even Destruction and Death say, \"only a rumour of it has reached our ears\" (v.22)."
          },
          {
            "word": "יִרְאַת",
            "transliteration": "yirʾāṭ",
            "gloss": "fear / reverence / awe",
            "paragraph": "\"The fear (yirʾāṭ) of the Lord — that is wisdom, and to shun evil is understanding\" (v.28). The chapter’s conclusion. After exhaustive searching, the answer: wisdom belongs to God, and the human path to wisdom is reverence. This is not anti-intellectual; it is the recognition that the deepest questions require relationship, not just research."
          }
        ],
        "cross": {
          "refs": [
            {
              "ref": "Prov 1:7",
              "note": "\"The fear of the LORD is the beginning of knowledge\" — the foundational wisdom principle, now confirmed."
            },
            {
              "ref": "Prov 9:10",
              "note": "\"The fear of the LORD is the beginning of wisdom\" — the Proverbs parallel to Job 28:28."
            },
            {
              "ref": "1 Cor 1:30",
              "note": "\"Christ Jesus, who has become for us wisdom from God\" — the NT identification of wisdom with a person."
            }
          ]
        },
        "mac": {
          "source": "MacArthur Study Bible — Faithful Paraphrase",
          "notes": [
            {
              "ref": "28:12–14",
              "note": "\"But where can wisdom be found? Where does understanding dwell? No mortal comprehends its worth; it cannot be found in the land of the living.\" Wisdom is not a commodity. It cannot be extracted like ore or traded like gold."
            },
            {
              "ref": "28:15–19",
              "note": "Gold, crystal, coral, jasper, rubies, topaz — none can buy wisdom. The most valuable things on earth cannot purchase the one thing that matters most."
            },
            {
              "ref": "28:20–22",
              "note": "\"Where then does wisdom come from? It is hidden from the eyes of every living thing... Destruction and Death say, ‘Only a rumour of it has reached our ears.’\" Even death’s realm has only heard whispers of wisdom."
            },
            {
              "ref": "28:23–28",
              "note": "\"God understands the way to it... when he established the force of the wind and measured out the waters, when he made a decree for the rain... he looked at wisdom and appraised it. And he said to the human race: ‘The fear of the Lord — that is wisdom.’\" The book’s theological foundation: wisdom is not information but relationship with God."
            }
          ]
        },
        "calvin": {
          "source": "John Calvin, Commentaries — Faithful Paraphrase",
          "notes": [
            {
              "ref": "28:28",
              "note": "Calvin: \"the fear of the Lord — that is wisdom\" is the book’s most important sentence. It will be confirmed in chapter 42 when Job, having encountered God, repents — not of sin but of speaking beyond his knowledge. Fear of the LORD is not terror but reverence before mystery."
            },
            {
              "ref": "28:15–19",
              "note": "Calvin: the inability of wealth to purchase wisdom condemns the entire transactional theology the friends offered: do good → get good. Wisdom transcends transaction."
            }
          ]
        },
        "net": {
          "source": "NET Bible Full Notes Edition — Biblical Studies Press",
          "notes": [
            {
              "ref": "28:12",
              "note": "The NET: the question \"where\" (meʾāyin) is emphatic — from what source? Wisdom’s origin is the question."
            },
            {
              "ref": "28:28",
              "note": "The NET: yirʾāṭ is not terror but reverential awe — the posture of a creature before its Creator. This is the same word used of Job in 1:1."
            }
          ]
        },
        "clines": {
          "source": "David J.A. Clines, Job, WBC (3 vols., 1989–2011) — Scholarly Paraphrase",
          "notes": [
            {
              "ref": "28:28",
              "note": "Clines: this verse is both the answer and the problem. If wisdom is the fear of the LORD, and Job already fears the LORD (1:1), then Job already has wisdom. So why is he suffering? The chapter deepens the mystery rather than resolving it."
            },
            {
              "ref": "28:23–27",
              "note": "Clines: God looked at wisdom \"when he established\" the world. Wisdom was present at creation — the same theology as Proverbs 8:22–31 where Wisdom was God’s companion at the beginning."
            }
          ]
        },
        "habel": {
          "source": "Norman C. Habel, The Book of Job, OTL (1985) — Scholarly Paraphrase",
          "notes": [
            {
              "ref": "28:12–28",
              "note": "Habel: the narrator declares what neither the friends nor Job could discover through argument: wisdom belongs to God alone. The human path to wisdom is not debate but reverence. This reframes the entire dialogue as a pursuit that, however brilliant, could never reach its goal."
            }
          ]
        },
        "hist": {
          "context": "The refrain \"where can wisdom be found?\" (vv.12, 20) structures the second half. Wisdom is not in the land of the living (v.13), not in the deep (v.14), cannot be purchased (vv.15–19), is hidden from every living thing (v.21), and even Death has only heard a rumour (v.22). Only God understands it (v.23). The conclusion (v.28) is the theological key to the entire book: the fear of the LORD is wisdom. Job’s friends had knowledge. Job himself had experience. Neither is wisdom. Wisdom is reverence before the God whose ways are beyond tracing."
        }
      }
    }
  ],
  "chapter_panels": {
    "ppl": [
      {
        "name": "Job",
        "role": "Key biblical figure",
        "text": "The voice shifts from Job to the narrator (or to a poetic interlude)…"
      },
      {
        "name": "God",
        "role": "Key biblical figure",
        "text": "Wisdom is reverence before the God whose ways are beyond tracing…"
      }
    ],
    "trans": "<tr><th>Version</th><th>Translation</th></tr><tr><td class=\"t-label\">NIV</td><td>Far from human dwellings they cut a shaft, in places untouched by human feet; far from other people they dangle and sway.</td></tr><tr><td class=\"t-label\">ESV</td><td>He opens shafts in a valley away from where anyone lives; they are forgotten by travelers; they hang in the air, far away from mankind; they swing to and fro.</td></tr><tr><td class=\"t-label\">NIV</td><td>The earth, from which food comes, is transformed below as by fire;</td></tr><tr><td class=\"t-label\">ESV</td><td>As for the earth, out of it comes bread, but underneath it is turned up as by fire.</td></tr>",
    "rec": [
      {
        "who": "John MacArthur",
        "text": "\"\"There is a mine for silver, a place where gold is refined. Iron is taken from the earth, copper smelted from ore.\" Human technology is celebrated: we can extract what is hidden.\""
      }
    ],
    "lit": {
      "rows": [
        {
          "label": "Human Achievement — 28:1–11",
          "text": "We mine gold, tunnel mountains, find sapphires. Our skill is immense.",
          "is_key": false
        },
        {
          "label": "The Question — 28:12–22",
          "text": "\"Where can wisdom be found?\" Not on land, not in the deep, not for sale. Even Death has only heard a rumour.",
          "is_key": false
        }
      ],
      "note": ""
    },
    "hebtext": [
      {
        "word": "מָקוֹם",
        "tlit": "māqōm",
        "gloss": "place / source / mine",
        "note": "\"There is a mine (māqōm) for silver and a place where gold is refined\" (v.1). The chapter opens with human technological achievement: mining, smelting, tunnelling. We can find silver, gold, iron, copper, sapphires — we can dig through rock and overturn mountains. Human ingenuity is extraordinary."
      },
      {
        "word": "חָכְמָה",
        "tlit": "ḥok̅mâ",
        "gloss": "wisdom",
        "note": "\"Where can wisdom (ḥok̅mâ) be found? Where does understanding dwell?\" (v.12). The question is repeated in v.20. Wisdom cannot be found in the land of the living (v.13), in the deep sea (v.14), or bought with gold, silver, onyx, or sapphire (vv.15–19). Even Destruction and Death say, \"only a rumour of it has reached our ears\" (v.22)."
      },
      {
        "word": "יִרְאַת",
        "tlit": "yirʾāṭ",
        "gloss": "fear / reverence / awe",
        "note": "\"The fear (yirʾāṭ) of the Lord — that is wisdom, and to shun evil is understanding\" (v.28). The chapter’s conclusion. After exhaustive searching, the answer: wisdom belongs to God, and the human path to wisdom is reverence. This is not anti-intellectual; it is the recognition that the deepest questions require relationship, not just research."
      }
    ],
    "thread": [
      {
        "anchor": "The Wisdom Hymn",
        "target": "Prov 2:4–5",
        "type": "Connection",
        "text": "\"Search for it as for hidden treasure... then you will understand the fear of the LORD\" — the same search metaphor.",
        "direction": "backward"
      },
      {
        "anchor": "The Wisdom Hymn",
        "target": "Prov 8:10–11",
        "type": "Connection",
        "text": "\"Choose my instruction instead of silver\" — wisdom valued above precious metals.",
        "direction": "backward"
      },
      {
        "anchor": "The Wisdom Hymn",
        "target": "Prov 1:7",
        "type": "Connection",
        "text": "\"The fear of the LORD is the beginning of knowledge\" — the foundational wisdom principle, now confirmed.",
        "direction": "backward"
      },
      {
        "anchor": "The Wisdom Hymn",
        "target": "Prov 9:10",
        "type": "Echo",
        "text": "\"The fear of the LORD is the beginning of wisdom\" — the Proverbs parallel to Job 28:28.",
        "direction": "backward"
      },
      {
        "anchor": "The Wisdom Hymn",
        "target": "1 Cor 1:30",
        "type": "Connection",
        "text": "\"Christ Jesus, who has become for us wisdom from God\" — the NT identification of wisdom with a person.",
        "direction": "backward"
      }
    ],
    "themes": {
      "scores": [
        {
          "label": "Covenant",
          "score": 10
        },
        {
          "label": "Judgment",
          "score": 8
        },
        {
          "label": "Mercy",
          "score": 8
        },
        {
          "label": "Faith",
          "score": 10
        },
        {
          "label": "Sovereignty",
          "score": 10
        },
        {
          "label": "Worship",
          "score": 10
        },
        {
          "label": "Holiness",
          "score": 10
        },
        {
          "label": "Prophecy",
          "score": 10
        },
        {
          "label": "Justice",
          "score": 10
        },
        {
          "label": "Mission",
          "score": 6
        }
      ],
      "note": "Holiness and Sovereignty peak: wisdom belongs to God alone. Worship rises: the fear of the LORD is the human path. Prophecy: wisdom at creation anticipates Proverbs 8 and Christ as wisdom (1 Cor 1:30)."
    }
  },
  "vhl_groups": [
    {
      "name": "divine",
      "css_class": "vhl-divine",
      "words": [
        "God",
        "LORD",
        "Spirit",
        "Angel",
        "Lord",
        "Holy Spirit",
        "Father",
        "Son",
        "I AM",
        "Almighty",
        "Shaddai"
      ],
      "btn_types": [
        "hebrew",
        "hebrew-text",
        "context"
      ]
    },
    {
      "name": "places",
      "css_class": "vhl-place",
      "words": [
        "Uz",
        "Edom",
        "Sheba",
        "Ophir",
        "Teman",
        "Jordan",
        "Egypt",
        "Rahab"
      ],
      "btn_types": [
        "places",
        "context"
      ]
    },
    {
      "name": "people",
      "css_class": "vhl-person",
      "words": [
        "Job",
        "Eliphaz",
        "Bildad",
        "Zophar",
        "Elihu",
        "Satan",
        "God",
        "Moses",
        "Abraham"
      ],
      "btn_types": [
        "people",
        "context"
      ]
    },
    {
      "name": "time",
      "css_class": "vhl-time",
      "words": [
        "day",
        "days",
        "night",
        "months",
        "years",
        "morning",
        "dawn"
      ],
      "btn_types": [
        "timeline",
        "context"
      ]
    },
    {
      "name": "key",
      "css_class": "vhl-key",
      "words": [
        "LORD",
        "God",
        "Almighty",
        "Shaddai",
        "righteous",
        "wicked",
        "wisdom",
        "justice",
        "suffering",
        "redeemer",
        "whirlwind",
        "dust",
        "ashes",
        "integrity",
        "counsel",
        "darkness",
        "light",
        "hope",
        "fear"
      ],
      "btn_types": [
        "literary",
        "cross"
      ]
    }
  ]
}