{
  "chapter_id": "pr24",
  "testament": "ot",
  "book_dir": "proverbs",
  "chapter_num": 24,
  "title": "Proverbs 24",
  "subtitle": "Do Not Envy Evil; Rescue the Staggering; The Sluggard's Field",
  "timeline_link": null,
  "map_story_link": null,
  "sections": [
    {
      "section_num": 1,
      "header": "Verses 1–18 — Do Not Envy Evil; Rescue the Staggering; Wisdom Builds the House",
      "verse_start": 1,
      "verse_end": 18,
      "panels": {
        "heb": [
          {
            "word": "הַצֵּל",
            "transliteration": "haṣṣēl",
            "gloss": "rescue/deliver",
            "paragraph": "Rescue (haṣṣēl) those being led away to death; hold back those staggering toward slaughter (v. 11). The imperative is urgent and unambiguous — there is no opt-out for bystanders. The verb nāṣal in the Hiphil means to snatch away, to physically intervene. The sage rejects the excuse 'we didn't know' (v. 12): God who weighs hearts knows what you knew."
          },
          {
            "word": "דְּבַשׁ",
            "transliteration": "dĕbaš",
            "gloss": "honey",
            "paragraph": "Wisdom is like dĕbaš (honey) to the soul — sweet when you find it (v. 14). Honey was the sweetest substance in the ancient world and a sign of the promised land's bounty. The comparison is sensory: wisdom is not duty but delight, an acquired taste that becomes the most satisfying flavour in life."
          }
        ],
        "ctx": "The first half of ch.24 contains the Thirty Sayings' wisdom-builds-the-house formula (v.3) and the obligation to rescue those staggering toward death (v.11). The honey-and-wisdom comparison (v.13-14) applies the sweetness metaphor: just as honey is good for the body, wisdom is good for the soul — with the same future-hope promise as 23:18.",
        "cross": [
          {
            "ref": "Prov 9:1",
            "note": "Wisdom has built her house — the personified Wisdom of ch.9 builds; wisdom in v.3 is the principle by which all houses are properly built."
          },
          {
            "ref": "Prov 14:4",
            "note": "Where there are no oxen the manger is clean, but abundant harvests come through the strength of an ox — the same diligence-requires-mess principle implicit in v.27."
          }
        ],
        "alter": {
          "source": "Robert Alter, The Hebrew Bible: A Translation with Commentary — Scholarly Paraphrase",
          "notes": [
            {
              "ref": "24:11-12",
              "note": "Rescue those led to death — the rhetorical question ('does not he who weighs the heart perceive it?') makes divine moral epistemology explicit: God evaluates what was known and withheld, not just what was done."
            },
            {
              "ref": "24:1",
              "note": "Do not envy evil men or desire to be with them — the chapter's answer to theodicy-envy is consistently temporal: the wicked have no future (v.20). Alter notes this is not denial of the present reality (the wicked do sometimes prosper) but insistence on the long view: the covenant framework evaluates outcomes over the full arc of a life, not at its peak of apparent success."
            }
          ]
        },
        "waltke": {
          "source": "Bruce K. Waltke, NICOT Commentary on Proverbs (2 vols.) — Scholarly Paraphrase",
          "notes": [
            {
              "ref": "24:11-12",
              "note": "Rescue those led to death; do not use ignorance as excuse — the God who weighs the heart knows what was known. The obligation to act for others in mortal danger cannot be discharged by selective ignorance."
            },
            {
              "ref": "24:1",
              "note": "Do not envy evil men — temporal reframe: the wicked have no future (v.20). Envy is stopped by seeing long-term reality, not by denying present appearances."
            }
          ]
        },
        "calvin": {
          "source": "John Calvin, Commentaries — Faithful Paraphrase",
          "notes": [
            {
              "ref": "24:11",
              "note": "Calvin: 'Those who are able to rescue the innocent and do not, offering the excuse of ignorance, are not acquitted — God who weighs the heart knows what they knew.'"
            },
            {
              "ref": "24:14",
              "note": "If you find wisdom, there is a future for you and your hope will not be cut off — wisdom is distinguished from all other earthly goods by the permanence of its benefit. Calvin notes that material prosperity can vanish overnight, reputation can be destroyed, health can fail. But wisdom, once genuinely acquired, cannot be taken away by any external circumstance."
            }
          ]
        },
        "net": {
          "source": "NET Bible Full Notes Edition — Biblical Studies Press",
          "notes": [
            {
              "ref": "24:11",
              "note": "NET: the rescue-instruction imposes a positive obligation to act, not merely permission. The disclaimer-rejection makes God the evaluator of what was known and decided."
            },
            {
              "ref": "24:5",
              "note": "The NET note on 'the wise have great power, and those with knowledge increase their strength' discusses the counter-intuitive claim: wisdom produces a kind of strength greater than physical power. The note traces the theme through Qohelet (Eccl 9:13-16: a poor wise man saved his city) and identifies wisdom as force-multiplier, not force-replacement."
            }
          ]
        }
      }
    },
    {
      "section_num": 2,
      "header": "Verses 19–34 — Do Not Fret Over Evildoers; The Field of the Sluggard; Second Collection Begins",
      "verse_start": 19,
      "verse_end": 34,
      "panels": {
        "heb": [
          {
            "word": "עָצֵל",
            "transliteration": "ʿāṣēl",
            "gloss": "sluggard",
            "paragraph": "The field of the ʿāṣēl (sluggard) passage (vv. 30–34) is an eyewitness account: 'I went past the field of the sluggard … thorns had come up everywhere, the ground was covered with weeds, and the stone wall was in ruins.' The sage reads the landscape as a moral text — neglect is visible, and poverty comes like an armed man."
          },
          {
            "word": "מַשְׂכִּיל",
            "transliteration": "maśkîl",
            "gloss": "one who has insight",
            "paragraph": "The wise observe and derive instruction — the process is called lāqaḥ mûsār (to take/receive discipline). The field of the sluggard is not merely a cautionary tale but a maśkîl moment: the discerning person can learn wisdom from negative examples. Every ruin tells a story if you have eyes to read it."
          }
        ],
        "ctx": "The second half includes more sayings from the supplementary collection (vv.23-29) and the extended parable of the sluggard's field (vv.30-34) — one of the most vivid portraits of lazy neglect in Proverbs. The field that produced only weeds because its owner loved sleep is the book's sharpest illustration of what happens when diligence is absent.",
        "cross": [
          {
            "ref": "Prov 6:10-11",
            "note": "A little sleep, a little slumber — the sluggard passage of ch.6 is echoed and extended in vv.30-34."
          },
          {
            "ref": "2 Thess 3:10",
            "note": "If anyone is not willing to work, let them not eat — the NT application of Proverbs' consistent diligence ethic."
          }
        ],
        "alter": {
          "source": "Robert Alter, The Hebrew Bible: A Translation with Commentary — Scholarly Paraphrase",
          "notes": [
            {
              "ref": "24:13-14",
              "note": "The honey-wisdom comparison — Alter notes the comparison is exact: present pleasure (taste) plus future benefit. Honey is genuinely pleasant; so is wisdom. Neither is merely obligatory."
            },
            {
              "ref": "24:30-34",
              "note": "The sluggard's field — unique in the proverb collections for its extended first-person observation. Wisdom as narrated personal experience, not just received tradition."
            }
          ]
        },
        "waltke": {
          "source": "Bruce K. Waltke, NICOT Commentary on Proverbs (2 vols.) — Scholarly Paraphrase",
          "notes": [
            {
              "ref": "24:13-14",
              "note": "Honey and wisdom — as honey is sweet to the taste, wisdom is sweet to the soul and has a future/hope (v.14). Wisdom's sweetness is both present and future; folly's sweetness is only present."
            },
            {
              "ref": "24:30-34",
              "note": "The sluggard's field — one of Proverbs' most sustained observational wisdom passages. The teacher observes, reflects, and draws the conclusion. The method is empirical: wisdom can be read from the observable world."
            }
          ]
        },
        "calvin": {
          "source": "John Calvin, Commentaries — Faithful Paraphrase",
          "notes": [
            {
              "ref": "24:16",
              "note": "Calvin: 'Though the righteous fall seven times, they rise again — the falling is not the mark of defeat; the rising is the mark of covenant faithfulness. The righteous person rises not because they never fail but because they have a foundation to rise from.'"
            },
            {
              "ref": "24:33",
              "note": "Calvin: 'A little sleep, a little slumber — the moderation of the laziness makes the warning more pointed. It is not gross idleness but comfortable small indulgences that destroy.'"
            }
          ]
        },
        "net": {
          "source": "NET Bible Full Notes Edition — Biblical Studies Press",
          "notes": [
            {
              "ref": "24:14",
              "note": "NET: wisdom's future/hope (yesh acharit) — the distinctive temporal promise. Unlike all material goods, wisdom's benefits extend into the future without diminishment."
            },
            {
              "ref": "24:33",
              "note": "NET: verbatim repetition of 6:10-11 — the same excuse used repeatedly produces the same result. The literary echo signals that the sluggard's self-deception is chronic, not occasional."
            }
          ]
        }
      }
    }
  ],
  "chapter_panels": {
    "ppl": [
      {
        "name": "The righteous",
        "role": "Walk blamelessly",
        "text": "Integrity is both compass and shield."
      },
      {
        "name": "The fool",
        "role": "Despises correction",
        "text": "Unteachable and self-destructive."
      },
      {
        "name": "The diligent",
        "role": "Plans and prospers",
        "text": "Patient work yields real gain."
      }
    ],
    "trans": "<tr><th>Version</th><th>Translation</th></tr><tr><td class=\"t-label\">NIV</td><td>\"By wisdom a house is built, and through understanding it is established; through knowledge its rooms are filled with rare and beautiful treasures.\"</td></tr><tr><td class=\"t-label\">Note</td><td>The Proverbs account of how excellent human life is constructed. Not by brute force but by cultivated intelligence and relational knowledge.</td></tr>",
    "src": [
      {
        "title": "Ancient Near Eastern wisdom",
        "quote": "These proverbs reflect Israel's engagement with international wisdom traditions, especially Egyptian.",
        "note": "Wisdom was a shared human enterprise across cultures."
      },
      {
        "title": "Hezekian editorial work",
        "quote": "Proverbs 25:1 notes that men of Hezekiah copied these proverbs — one of the most historically specific attributions in Proverbs.",
        "note": "The editorial activity shows Proverbs as a living, curated collection."
      }
    ],
    "rec": [
      {
        "who": "Virtue ethics",
        "text": "Proverbs 21-30 has been foundational to Christian virtue ethics — the practical outworking of the fear of the LORD."
      },
      {
        "who": "Practical wisdom",
        "text": "These chapters have been widely cited in ethics, governance, and social teaching."
      }
    ],
    "lit": {
      "rows": [
        {
          "label": "Rescue the Staggering",
          "text": "Rescue those being led away to death; hold back those staggering toward slaughter. If you say I did not know about this -- does not he who weighs the heart perceive it? The positive obligation to act for others in mortal danger cannot be discharged by selective ignorance.",
          "is_key": false
        },
        {
          "label": "The Sluggard's Field: Empirical Wisdom",
          "text": "I went past the field of a sluggard... thorns had come up everywhere, the ground was covered with weeds. First-person observation, reflection, conclusion: wisdom can be read from the observable world.",
          "is_key": false
        }
      ],
      "note": ""
    },
    "tx": [
      {
        "ref": "24:23–34",
        "title": "Additional 'Sayings of the Wise' — placement in LXX",
        "content": "MT places a second 'Sayings of the Wise' collection at the end of chapter 24. In the LXX, this material appears in a completely different location — after chapter 30 (Agur) rather than in its MT position. This is one of the most dramatic structural differences in LXX Proverbs.",
        "note": "The LXX's placement of the supplementary wisdom collection after Agur's sayings creates a different reading experience, grouping shorter collections together rather than interspersing them with Solomonic material."
      }
    ],
    "debate": [
      {
        "title": "Proverbs' Empirical Method: Observation as a Source of Wisdom",
        "positions": [
          {
            "name": "Valid source alongside revelation",
            "proponents": "Waltke, most OT wisdom scholars",
            "argument": "The sluggard's-field observation exemplifies the empirical method: observe the world carefully and draw theological conclusions. Observation-based wisdom is a valid route to knowledge."
          },
          {
            "name": "Creation observation as general revelation",
            "proponents": "Calvin, Reformed tradition",
            "argument": "Wisdom read from creation expresses natural law embedded within it. God's wisdom is in the structure of things."
          }
        ]
      }
    ],
    "themes": {
      "scores": [],
      "note": ""
    }
  },
  "vhl_groups": [
    {
      "name": "divine",
      "css_class": "vhl-divine",
      "words": [
        "God",
        "LORD",
        "Spirit",
        "Angel",
        "Lord",
        "Holy Spirit",
        "Father",
        "Son",
        "I AM",
        "Almighty",
        "Shaddai"
      ],
      "btn_types": [
        "hebrew",
        "hebrew-text",
        "context"
      ]
    },
    {
      "name": "places",
      "css_class": "vhl-place",
      "words": [
        "gate",
        "city",
        "market",
        "field",
        "house",
        "street",
        "court",
        "path",
        "way"
      ],
      "btn_types": [
        "places",
        "context"
      ]
    },
    {
      "name": "people",
      "css_class": "vhl-person",
      "words": [
        "LORD",
        "king",
        "fool",
        "wise",
        "righteous",
        "wicked",
        "poor",
        "rich",
        "son",
        "wife",
        "neighbour"
      ],
      "btn_types": [
        "people",
        "context"
      ]
    },
    {
      "name": "time",
      "css_class": "vhl-time",
      "words": [
        "day",
        "days",
        "morning",
        "evening",
        "year",
        "life",
        "age",
        "generation"
      ],
      "btn_types": [
        "timeline",
        "context"
      ]
    },
    {
      "name": "key",
      "css_class": "vhl-key",
      "words": [
        "wisdom",
        "knowledge",
        "understanding",
        "fear",
        "righteous",
        "wicked",
        "heart",
        "tongue",
        "mouth",
        "honour",
        "pride",
        "humility"
      ],
      "btn_types": [
        "literary",
        "cross"
      ]
    }
  ]
}